spotfire_dsml/__init__.py
spotfire_dsml/distribution_fitting/__init__.py
spotfire_dsml/distribution_fitting/distribution_fitting.py
spotfire_dsml/geo_analytics/__init__.py
spotfire_dsml/geo_analytics/crs_utilities.py
spotfire_dsml/geo_analytics/distances.py
spotfire_dsml/geo_analytics/io_utilities.py
spotfire_dsml/geo_analytics/shape_utilities.py
spotfire_dsml/geo_analytics/spatial_joins.py
spotfire_dsml/missing_data/__init__.py
spotfire_dsml/missing_data/evaluation.py
spotfire_dsml/missing_data/preprocessing.py
spotfire_dsml/ml_drift/__init__.py
spotfire_dsml/ml_drift/drift_data.py
spotfire_dsml/ml_explain/__init__.py
spotfire_dsml/ml_explain/ml_explain.py
spotfire_dsml/ml_metadata/__init__.py
spotfire_dsml/ml_metadata/metadata_data.py
spotfire_dsml/ml_metadata/metadata_model.py
spotfire_dsml/ml_modeling/__init__.py
spotfire_dsml/ml_modeling/ml_modeling.py
spotfire_dsml/nlp_preprocessing/__init__.py
spotfire_dsml/nlp_preprocessing/features.py
spotfire_dsml/nlp_preprocessing/search_and_clustering.py
spotfire_dsml/nlp_preprocessing/topic_modeling.py
spotfire_dsml/time_series/__init__.py
spotfire_dsml/time_series/api.py
spotfire_dsml/time_series/decomposing.py
spotfire_dsml/time_series/forecasting.py
spotfire_dsml/time_series/pattern_exploration.py
spotfire_dsml/time_series/preprocessing.py
spotfire_dsml/time_series/smoothing.py
tests/time_series/__init__.py
tests/time_series/conftest.py
tests/time_series/test_decomposing.py
tests/time_series/test_forecasting.py
tests/time_series/test_pattern_exploration.py
tests/time_series/test_preprocessing.py
tests/time_series/test_sax_encoding.py
tests/time_series/test_smoothing.py
spotfire_dsml-1.1.3.dist-info/LICENSE
spotfire_dsml-1.1.3.dist-info/METADATA
spotfire_dsml-1.1.3.dist-info/WHEEL
spotfire_dsml-1.1.3.dist-info/entry_points.txt
spotfire_dsml-1.1.3.dist-info/top_level.txt
spotfire_dsml-1.1.3.dist-info/RECORD
