Metadata-Version: 2.1
Name: spotfire-dsml
Version: 1.1.3
Summary: Toolkit for data science and machine learning built by Spotfire
Home-page: https://community.spotfire.com/articles/spotfire/python-toolkit-for-data-science-and-machine-learning-in-spotfire/
Maintainer: Spotfire Python Package Support
Maintainer-email: spotfirepython@tibco.com
License: BSD License (BSD 3-Clause License)
Classifier: Development Status :: 5 - Production/Stable
Classifier: Intended Audience :: Developers
Classifier: Programming Language :: Python :: 3
Classifier: Operating System :: Unix
Classifier: Operating System :: MacOS :: MacOS X
Classifier: Operating System :: Microsoft :: Windows
Requires-Python: >=3.11, <4
License-File: LICENSE
Requires-Dist: pandas==2.0.3
Requires-Dist: scikit-learn==1.3.0
Requires-Dist: tensorflow==2.13.0
Requires-Dist: numpy==1.24.3
Requires-Dist: fastapi==0.100.0
Requires-Dist: uvicorn==0.18.3
Requires-Dist: category-encoders==2.5.0
Requires-Dist: matplotlib==3.7.2
Requires-Dist: seaborn==0.12.2
Requires-Dist: scikeras==0.11.0
Requires-Dist: xgboost==1.7.6
Requires-Dist: cloudpickle==2.2.1
Requires-Dist: mlxtend==0.21.0
Requires-Dist: supersmoother==0.4
Requires-Dist: statsmodels==0.14.0
Requires-Dist: nltk==3.8.1
Requires-Dist: distfit==1.7.1
Requires-Dist: scipy==1.10.1
Requires-Dist: geopandas==0.14.3
Requires-Dist: shapely==2.0.2
Requires-Dist: pyproj==3.6.1
Requires-Dist: geopy==2.4.1
Requires-Dist: pyogrio==0.7.2
Requires-Dist: bertopic==0.16.2
Requires-Dist: hdbscan==0.8.36
Requires-Dist: rank-bm25==0.2.2
Requires-Dist: sentence-transformers==3.0.0
Requires-Dist: torch==2.1.2
Requires-Dist: stumpy==1.12.0
Provides-Extra: dev
Requires-Dist: pytest==7.1.3; extra == "dev"
Requires-Dist: pytest-cov==4.0.0; extra == "dev"
Requires-Dist: pylint==2.15.3; extra == "dev"
Requires-Dist: black==24.3.0; extra == "dev"
Requires-Dist: mypy==0.982; extra == "dev"
Requires-Dist: fire==0.4.0; extra == "dev"
